hatched/__init__.py
hatched/hatched.py
hatched/vpype_plugin.py
hatched-0.2.0.dist-info/LICENSE
hatched-0.2.0.dist-info/METADATA
hatched-0.2.0.dist-info/WHEEL
hatched-0.2.0.dist-info/entry_points.txt
hatched-0.2.0.dist-info/top_level.txt
hatched-0.2.0.dist-info/RECORD
