Metadata-Version: 2.1
Name: hatched
Version: 0.2.0
Summary: Convert images to plotter-friendly hatched patterns
Home-page: https://github.com/plottertools/hatched
Author: Antoine Beyeler
Author-email: abeyeler@gmail.com
License: UNKNOWN
Platform: UNKNOWN
Classifier: Programming Language :: Python :: 3
Classifier: License :: OSI Approved :: MIT License
Classifier: Operating System :: OS Independent
Classifier: Development Status :: 4 - Beta
Classifier: Topic :: Multimedia :: Graphics
Classifier: Environment :: Plugins
License-File: LICENSE
Requires-Dist: click
Requires-Dist: vpype[all] (<2.0,>=1.10)
Requires-Dist: scikit-image
Requires-Dist: svgwrite
Requires-Dist: shapely (>=1.8)
Requires-Dist: matplotlib
Requires-Dist: opencv-python-headless
